{
    "price": {
        "current": {
            "datetime": "2023-01-05 00:00:00",
            "count": 405.0,
            "mean": 109.27654320987655,
            "std": 27.43367461483258,
            "min": 100.0,
            "25%": 100.0,
            "50%": 100.0,
            "75%": 120.0,
            "max": 600.0
        },
        "summary7Days": {
            "datetime": "2023-01-05 00:00:00",
            "count": 70.0,
            "mean": 1.9840058964437048,
            "std": -3.2960400487181403,
            "min": 0.0,
            "25%": 0.0,
            "50%": 0.0,
            "75%": 0.0,
            "max": 0.0
        },
        "volatility": {
            "weekly": {
                "min": {
                    "basePrice": 100.0,
                    "latestPrice": 100.0,
                    "percent": 0.0
                },
                "50%": {
                    "basePrice": 100.0,
                    "latestPrice": 100.0,
                    "percent": 0.0
                }
            },
            "daily": {
                "min": {
                    "basePrice": 100.0,
                    "latestPrice": 100.0,
                    "percent": 0.0
                },
                "50%": {
                    "basePrice": 100.0,
                    "latestPrice": 100.0,
                    "percent": 0.0
                }
            }
        },
        "weekly": {
            "archive": {
                "count": 7,
                "data": [
                    {
                        "datetime": "2022-12-30 00:00:00",
                        "count": 335.0,
                        "mean": 107.29253731343285,
                        "std": 30.72971466355072,
                        "min": 100.0,
                        "25%": 100.0,
                        "50%": 100.0,
                        "75%": 120.0,
                        "max": 600.0
                    },
                    {
                        "datetime": "2022-12-31 00:00:00",
                        "count": 333.0,
                        "mean": 107.08408408408408,
                        "std": 30.06667518639188,
                        "min": 100.0,
                        "25%": 100.0,
                        "50%": 100.0,
                        "75%": 100.0,
                        "max": 600.0
                    },
                    {
                        "datetime": "2023-01-01 00:00:00",
                        "count": 332.0,
                        "mean": 107.03915662650604,
                        "std": 29.805740184183577,
                        "min": 100.0,
                        "25%": 100.0,
                        "50%": 100.0,
                        "75%": 105.0,
                        "max": 600.0
                    },
                    {
                        "datetime": "2023-01-02 00:00:00",
                        "count": 403.0,
                        "mean": 109.3225806451613,
                        "std": 27.49400950203213,
                        "min": 100.0,
                        "25%": 100.0,
                        "50%": 100.0,
                        "75%": 120.0,
                        "max": 600.0
                    },
                    {
                        "datetime": "2023-01-03 00:00:00",
                        "count": 404.0,
                        "mean": 109.3490099009901,
                        "std": 27.46501449753445,
                        "min": 100.0,
                        "25%": 100.0,
                        "50%": 100.0,
                        "75%": 120.0,
                        "max": 600.0
                    },
                    {
                        "datetime": "2023-01-04 00:00:00",
                        "count": 407.0,
                        "mean": 109.28009828009829,
                        "std": 27.375066358246443,
                        "min": 100.0,
                        "25%": 100.0,
                        "50%": 100.0,
                        "75%": 120.0,
                        "max": 600.0
                    },
                    {
                        "datetime": "2023-01-05 00:00:00",
                        "count": 405.0,
                        "mean": 109.27654320987655,
                        "std": 27.43367461483258,
                        "min": 100.0,
                        "25%": 100.0,
                        "50%": 100.0,
                        "75%": 120.0,
                        "max": 600.0
                    }
                ]
            },
            "diff": {
                "count": 7,
                "data": [
                    {
                        "datetime": "2022-12-30 00:00:00",
                        "count": null,
                        "mean": null,
                        "std": null,
                        "min": null,
                        "25%": null,
                        "50%": null,
                        "75%": null,
                        "max": null
                    },
                    {
                        "datetime": "2022-12-31 00:00:00",
                        "count": -2.0,
                        "mean": -0.20845322934876265,
                        "std": -0.6630394771588399,
                        "min": 0.0,
                        "25%": 0.0,
                        "50%": 0.0,
                        "75%": -20.0,
                        "max": 0.0
                    },
                    {
                        "datetime": "2023-01-01 00:00:00",
                        "count": -1.0,
                        "mean": -0.04492745757804073,
                        "std": -0.2609350022083028,
                        "min": 0.0,
                        "25%": 0.0,
                        "50%": 0.0,
                        "75%": 5.0,
                        "max": 0.0
                    },
                    {
                        "datetime": "2023-01-02 00:00:00",
                        "count": 71.0,
                        "mean": 2.2834240186552535,
                        "std": -2.3117306821514454,
                        "min": 0.0,
                        "25%": 0.0,
                        "50%": 0.0,
                        "75%": 15.0,
                        "max": 0.0
                    },
                    {
                        "datetime": "2023-01-03 00:00:00",
                        "count": 1.0,
                        "mean": 0.026429255828801956,
                        "std": -0.028995004497680554,
                        "min": 0.0,
                        "25%": 0.0,
                        "50%": 0.0,
                        "75%": 0.0,
                        "max": 0.0
                    },
                    {
                        "datetime": "2023-01-04 00:00:00",
                        "count": 3.0,
                        "mean": -0.0689116208918108,
                        "std": -0.08994813928800838,
                        "min": 0.0,
                        "25%": 0.0,
                        "50%": 0.0,
                        "75%": 0.0,
                        "max": 0.0
                    },
                    {
                        "datetime": "2023-01-05 00:00:00",
                        "count": -2.0,
                        "mean": -0.0035550702217364005,
                        "std": 0.058608256586136775,
                        "min": 0.0,
                        "25%": 0.0,
                        "50%": 0.0,
                        "75%": 0.0,
                        "max": 0.0
                    }
                ]
            }
        },
        "halfYear": {
            "archive": {
                "count": 13,
                "data": [
                    {
                        "datetime": "2022-07-21 00:00:00",
                        "count": 0.0,
                        "mean": 0.0,
                        "std": 0.0,
                        "min": 0.0,
                        "25%": 0.0,
                        "50%": 0.0,
                        "75%": 0.0,
                        "max": 0.0
                    },
                    {
                        "datetime": "2022-08-04 00:00:00",
                        "count": 0.0,
                        "mean": 0.0,
                        "std": 0.0,
                        "min": 0.0,
                        "25%": 0.0,
                        "50%": 0.0,
                        "75%": 0.0,
                        "max": 0.0
                    },
                    {
                        "datetime": "2022-08-18 00:00:00",
                        "count": 475.0,
                        "mean": 164.9978947368421,
                        "std": 41.87007727585349,
                        "min": 120.0,
                        "25%": 120.0,
                        "50%": 200.0,
                        "75%": 200.0,
                        "max": 450.0
                    },
                    {
                        "datetime": "2022-09-01 00:00:00",
                        "count": 505.0,
                        "mean": 145.61188118811882,
                        "std": 61.31967900405594,
                        "min": 80.0,
                        "25%": 80.0,
                        "50%": 200.0,
                        "75%": 200.0,
                        "max": 450.0
                    },
                    {
                        "datetime": "2022-09-15 00:00:00",
                        "count": 498.0,
                        "mean": 102.51807228915662,
                        "std": 25.711537755281043,
                        "min": 80.0,
                        "25%": 80.0,
                        "50%": 120.0,
                        "75%": 120.0,
                        "max": 450.0
                    },
                    {
                        "datetime": "2022-09-29 00:00:00",
                        "count": 519.0,
                        "mean": 115.8843930635838,
                        "std": 38.128644862388086,
                        "min": 80.0,
                        "25%": 80.0,
                        "50%": 150.0,
                        "75%": 150.0,
                        "max": 450.0
                    },
                    {
                        "datetime": "2022-10-13 00:00:00",
                        "count": 478.0,
                        "mean": 91.84937238493724,
                        "std": 11.127350745606778,
                        "min": 80.0,
                        "25%": 80.0,
                        "50%": 100.0,
                        "75%": 100.0,
                        "max": 204.0
                    },
                    {
                        "datetime": "2022-10-27 00:00:00",
                        "count": 368.0,
                        "mean": 95.5,
                        "std": 10.250805776794792,
                        "min": 80.0,
                        "25%": 100.0,
                        "50%": 100.0,
                        "75%": 100.0,
                        "max": 204.0
                    },
                    {
                        "datetime": "2022-11-10 00:00:00",
                        "count": 275.0,
                        "mean": 97.83272727272728,
                        "std": 36.14267679074879,
                        "min": 80.0,
                        "25%": 90.0,
                        "50%": 100.0,
                        "75%": 100.0,
                        "max": 660.0
                    },
                    {
                        "datetime": "2022-11-24 00:00:00",
                        "count": 264.0,
                        "mean": 105.3181818181818,
                        "std": 35.77226620415969,
                        "min": 100.0,
                        "25%": 100.0,
                        "50%": 100.0,
                        "75%": 100.0,
                        "max": 660.0
                    },
                    {
                        "datetime": "2022-12-08 00:00:00",
                        "count": 357.0,
                        "mean": 106.6778711484594,
                        "std": 28.30888787172524,
                        "min": 100.0,
                        "25%": 100.0,
                        "50%": 100.0,
                        "75%": 100.0,
                        "max": 600.0
                    },
                    {
                        "datetime": "2022-12-22 00:00:00",
                        "count": 336.0,
                        "mean": 91.38095238095238,
                        "std": 33.477782255727526,
                        "min": 80.0,
                        "25%": 80.0,
                        "50%": 80.0,
                        "75%": 80.0,
                        "max": 600.0
                    },
                    {
                        "datetime": "2023-01-05 00:00:00",
                        "count": 405.0,
                        "mean": 109.27654320987655,
                        "std": 27.43367461483258,
                        "min": 100.0,
                        "25%": 100.0,
                        "50%": 100.0,
                        "75%": 120.0,
                        "max": 600.0
                    }
                ]
            },
            "diff": {
                "count": 13,
                "data": [
                    {
                        "datetime": "2022-07-21 00:00:00",
                        "count": null,
                        "mean": null,
                        "std": null,
                        "min": null,
                        "25%": null,
                        "50%": null,
                        "75%": null,
                        "max": null
                    },
                    {
                        "datetime": "2022-08-04 00:00:00",
                        "count": 0.0,
                        "mean": 0.0,
                        "std": 0.0,
                        "min": 0.0,
                        "25%": 0.0,
                        "50%": 0.0,
                        "75%": 0.0,
                        "max": 0.0
                    },
                    {
                        "datetime": "2022-08-18 00:00:00",
                        "count": 475.0,
                        "mean": 164.9978947368421,
                        "std": 41.87007727585349,
                        "min": 120.0,
                        "25%": 120.0,
                        "50%": 200.0,
                        "75%": 200.0,
                        "max": 450.0
                    },
                    {
                        "datetime": "2022-09-01 00:00:00",
                        "count": 30.0,
                        "mean": -19.386013548723298,
                        "std": 19.449601728202452,
                        "min": -40.0,
                        "25%": -40.0,
                        "50%": 0.0,
                        "75%": 0.0,
                        "max": 0.0
                    },
                    {
                        "datetime": "2022-09-15 00:00:00",
                        "count": -7.0,
                        "mean": -43.093808898962195,
                        "std": -35.6081412487749,
                        "min": 0.0,
                        "25%": 0.0,
                        "50%": -80.0,
                        "75%": -80.0,
                        "max": 0.0
                    },
                    {
                        "datetime": "2022-09-29 00:00:00",
                        "count": 21.0,
                        "mean": 13.36632077442718,
                        "std": 12.417107107107043,
                        "min": 0.0,
                        "25%": 0.0,
                        "50%": 30.0,
                        "75%": 30.0,
                        "max": 0.0
                    },
                    {
                        "datetime": "2022-10-13 00:00:00",
                        "count": -41.0,
                        "mean": -24.03502067864656,
                        "std": -27.00129411678131,
                        "min": 0.0,
                        "25%": 0.0,
                        "50%": -50.0,
                        "75%": -50.0,
                        "max": -246.0
                    },
                    {
                        "datetime": "2022-10-27 00:00:00",
                        "count": -110.0,
                        "mean": 3.65062761506276,
                        "std": -0.8765449688119862,
                        "min": 0.0,
                        "25%": 20.0,
                        "50%": 0.0,
                        "75%": 0.0,
                        "max": 0.0
                    },
                    {
                        "datetime": "2022-11-10 00:00:00",
                        "count": -93.0,
                        "mean": 2.3327272727272828,
                        "std": 25.891871013953995,
                        "min": 0.0,
                        "25%": -10.0,
                        "50%": 0.0,
                        "75%": 0.0,
                        "max": 456.0
                    },
                    {
                        "datetime": "2022-11-24 00:00:00",
                        "count": -11.0,
                        "mean": 7.485454545454516,
                        "std": -0.3704105865890952,
                        "min": 20.0,
                        "25%": 10.0,
                        "50%": 0.0,
                        "75%": 0.0,
                        "max": 0.0
                    },
                    {
                        "datetime": "2022-12-08 00:00:00",
                        "count": 93.0,
                        "mean": 1.3596893302776039,
                        "std": -7.463378332434452,
                        "min": 0.0,
                        "25%": 0.0,
                        "50%": 0.0,
                        "75%": 0.0,
                        "max": -60.0
                    },
                    {
                        "datetime": "2022-12-22 00:00:00",
                        "count": -21.0,
                        "mean": -15.296918767507023,
                        "std": 5.168894384002286,
                        "min": -20.0,
                        "25%": -20.0,
                        "50%": -20.0,
                        "75%": -20.0,
                        "max": 0.0
                    },
                    {
                        "datetime": "2023-01-05 00:00:00",
                        "count": 69.0,
                        "mean": 17.89559082892417,
                        "std": -6.044107640894946,
                        "min": 20.0,
                        "25%": 20.0,
                        "50%": 20.0,
                        "75%": 40.0,
                        "max": 0.0
                    }
                ]
            }
        },
        "OneYear": {
            "archive": {
                "count": 0,
                "data": []
            },
            "diff": {
                "count": 0,
                "data": []
            }
        }
    },
    "calc": {
        "latest_date": "2023-01-05 00:00:00",
        "updated_at": "2023-01-05 20:16:02"
    }
}