{
    "price": {
        "current": {
            "datetime": "2022-11-22 00:00:00",
            "count": 153.0,
            "mean": 101.59477124183006,
            "std": 14.129773487073654,
            "min": 100.0,
            "25%": 100.0,
            "50%": 100.0,
            "75%": 100.0,
            "max": 244.0
        },
        "summary7Days": {
            "datetime": "2022-11-22 00:00:00",
            "count": -16.0,
            "mean": 4.292996093901053,
            "std": -1.9625215983331241,
            "min": 20.0,
            "25%": 0.0,
            "50%": 0.0,
            "75%": 0.0,
            "max": 0.0
        },
        "volatility": {
            "weekly": {
                "min": {
                    "basePrice": 80.0,
                    "latestPrice": 100.0,
                    "percent": 25.0
                },
                "50%": {
                    "basePrice": 100.0,
                    "latestPrice": 100.0,
                    "percent": 0.0
                }
            },
            "daily": {
                "min": {
                    "basePrice": 80.0,
                    "latestPrice": 100.0,
                    "percent": 25.0
                },
                "50%": {
                    "basePrice": 100.0,
                    "latestPrice": 100.0,
                    "percent": 0.0
                }
            }
        },
        "weekly": {
            "archive": {
                "count": 7,
                "data": [
                    {
                        "datetime": "2022-11-16 00:00:00",
                        "count": 169.0,
                        "mean": 97.301775147929,
                        "std": 16.09229508540678,
                        "min": 80.0,
                        "25%": 100.0,
                        "50%": 100.0,
                        "75%": 100.0,
                        "max": 244.0
                    },
                    {
                        "datetime": "2022-11-17 00:00:00",
                        "count": 169.0,
                        "mean": 97.301775147929,
                        "std": 16.09229508540678,
                        "min": 80.0,
                        "25%": 100.0,
                        "50%": 100.0,
                        "75%": 100.0,
                        "max": 244.0
                    },
                    {
                        "datetime": "2022-11-18 00:00:00",
                        "count": 171.0,
                        "mean": 97.09941520467837,
                        "std": 16.105773524810086,
                        "min": 80.0,
                        "25%": 100.0,
                        "50%": 100.0,
                        "75%": 100.0,
                        "max": 244.0
                    },
                    {
                        "datetime": "2022-11-19 00:00:00",
                        "count": 171.0,
                        "mean": 97.09941520467837,
                        "std": 16.105773524810086,
                        "min": 80.0,
                        "25%": 100.0,
                        "50%": 100.0,
                        "75%": 100.0,
                        "max": 244.0
                    },
                    {
                        "datetime": "2022-11-20 00:00:00",
                        "count": 184.0,
                        "mean": 97.95652173913044,
                        "std": 15.215690092600475,
                        "min": 80.0,
                        "25%": 100.0,
                        "50%": 100.0,
                        "75%": 100.0,
                        "max": 244.0
                    },
                    {
                        "datetime": "2022-11-21 00:00:00",
                        "count": 174.0,
                        "mean": 98.98850574712644,
                        "std": 15.006352606931191,
                        "min": 80.0,
                        "25%": 100.0,
                        "50%": 100.0,
                        "75%": 100.0,
                        "max": 244.0
                    },
                    {
                        "datetime": "2022-11-22 00:00:00",
                        "count": 153.0,
                        "mean": 101.59477124183006,
                        "std": 14.129773487073654,
                        "min": 100.0,
                        "25%": 100.0,
                        "50%": 100.0,
                        "75%": 100.0,
                        "max": 244.0
                    }
                ]
            },
            "diff": {
                "count": 7,
                "data": [
                    {
                        "datetime": "2022-11-16 00:00:00",
                        "count": null,
                        "mean": null,
                        "std": null,
                        "min": null,
                        "25%": null,
                        "50%": null,
                        "75%": null,
                        "max": null
                    },
                    {
                        "datetime": "2022-11-17 00:00:00",
                        "count": 0.0,
                        "mean": 0.0,
                        "std": 0.0,
                        "min": 0.0,
                        "25%": 0.0,
                        "50%": 0.0,
                        "75%": 0.0,
                        "max": 0.0
                    },
                    {
                        "datetime": "2022-11-18 00:00:00",
                        "count": 2.0,
                        "mean": -0.20235994325064155,
                        "std": 0.013478439403307618,
                        "min": 0.0,
                        "25%": 0.0,
                        "50%": 0.0,
                        "75%": 0.0,
                        "max": 0.0
                    },
                    {
                        "datetime": "2022-11-19 00:00:00",
                        "count": 0.0,
                        "mean": 0.0,
                        "std": 0.0,
                        "min": 0.0,
                        "25%": 0.0,
                        "50%": 0.0,
                        "75%": 0.0,
                        "max": 0.0
                    },
                    {
                        "datetime": "2022-11-20 00:00:00",
                        "count": 13.0,
                        "mean": 0.8571065344520719,
                        "std": -0.890083432209611,
                        "min": 0.0,
                        "25%": 0.0,
                        "50%": 0.0,
                        "75%": 0.0,
                        "max": 0.0
                    },
                    {
                        "datetime": "2022-11-21 00:00:00",
                        "count": -10.0,
                        "mean": 1.0319840079960017,
                        "std": -0.209337485669284,
                        "min": 0.0,
                        "25%": 0.0,
                        "50%": 0.0,
                        "75%": 0.0,
                        "max": 0.0
                    },
                    {
                        "datetime": "2022-11-22 00:00:00",
                        "count": -21.0,
                        "mean": 2.606265494703621,
                        "std": -0.8765791198575368,
                        "min": 20.0,
                        "25%": 0.0,
                        "50%": 0.0,
                        "75%": 0.0,
                        "max": 0.0
                    }
                ]
            }
        },
        "halfYear": {
            "archive": {
                "count": 13,
                "data": [
                    {
                        "datetime": "2022-06-07 00:00:00",
                        "count": 0.0,
                        "mean": 0.0,
                        "std": 0.0,
                        "min": 0.0,
                        "25%": 0.0,
                        "50%": 0.0,
                        "75%": 0.0,
                        "max": 0.0
                    },
                    {
                        "datetime": "2022-06-21 00:00:00",
                        "count": 0.0,
                        "mean": 0.0,
                        "std": 0.0,
                        "min": 0.0,
                        "25%": 0.0,
                        "50%": 0.0,
                        "75%": 0.0,
                        "max": 0.0
                    },
                    {
                        "datetime": "2022-07-05 00:00:00",
                        "count": 0.0,
                        "mean": 0.0,
                        "std": 0.0,
                        "min": 0.0,
                        "25%": 0.0,
                        "50%": 0.0,
                        "75%": 0.0,
                        "max": 0.0
                    },
                    {
                        "datetime": "2022-07-19 00:00:00",
                        "count": 0.0,
                        "mean": 0.0,
                        "std": 0.0,
                        "min": 0.0,
                        "25%": 0.0,
                        "50%": 0.0,
                        "75%": 0.0,
                        "max": 0.0
                    },
                    {
                        "datetime": "2022-08-02 00:00:00",
                        "count": 0.0,
                        "mean": 0.0,
                        "std": 0.0,
                        "min": 0.0,
                        "25%": 0.0,
                        "50%": 0.0,
                        "75%": 0.0,
                        "max": 0.0
                    },
                    {
                        "datetime": "2022-08-16 00:00:00",
                        "count": 0.0,
                        "mean": 0.0,
                        "std": 0.0,
                        "min": 0.0,
                        "25%": 0.0,
                        "50%": 0.0,
                        "75%": 0.0,
                        "max": 0.0
                    },
                    {
                        "datetime": "2022-08-30 00:00:00",
                        "count": 292.0,
                        "mean": 105.56164383561644,
                        "std": 42.80154357025483,
                        "min": 80.0,
                        "25%": 80.0,
                        "50%": 80.0,
                        "75%": 150.0,
                        "max": 550.0
                    },
                    {
                        "datetime": "2022-09-13 00:00:00",
                        "count": 263.0,
                        "mean": 108.03802281368822,
                        "std": 44.19956563341639,
                        "min": 80.0,
                        "25%": 80.0,
                        "50%": 80.0,
                        "75%": 150.0,
                        "max": 550.0
                    },
                    {
                        "datetime": "2022-09-27 00:00:00",
                        "count": 231.0,
                        "mean": 91.83549783549785,
                        "std": 33.45585988301529,
                        "min": 80.0,
                        "25%": 80.0,
                        "50%": 80.0,
                        "75%": 100.0,
                        "max": 550.0
                    },
                    {
                        "datetime": "2022-10-11 00:00:00",
                        "count": 233.0,
                        "mean": 89.80257510729614,
                        "std": 14.219176957202542,
                        "min": 80.0,
                        "25%": 80.0,
                        "50%": 80.0,
                        "75%": 100.0,
                        "max": 244.0
                    },
                    {
                        "datetime": "2022-10-25 00:00:00",
                        "count": 231.0,
                        "mean": 90.32034632034632,
                        "std": 14.248156917009114,
                        "min": 80.0,
                        "25%": 80.0,
                        "50%": 80.0,
                        "75%": 100.0,
                        "max": 244.0
                    },
                    {
                        "datetime": "2022-11-08 00:00:00",
                        "count": 215.0,
                        "mean": 94.06511627906976,
                        "std": 19.037970957729463,
                        "min": 80.0,
                        "25%": 80.0,
                        "50%": 100.0,
                        "75%": 100.0,
                        "max": 280.0
                    },
                    {
                        "datetime": "2022-11-22 00:00:00",
                        "count": 153.0,
                        "mean": 101.59477124183006,
                        "std": 14.129773487073654,
                        "min": 100.0,
                        "25%": 100.0,
                        "50%": 100.0,
                        "75%": 100.0,
                        "max": 244.0
                    }
                ]
            },
            "diff": {
                "count": 13,
                "data": [
                    {
                        "datetime": "2022-06-07 00:00:00",
                        "count": null,
                        "mean": null,
                        "std": null,
                        "min": null,
                        "25%": null,
                        "50%": null,
                        "75%": null,
                        "max": null
                    },
                    {
                        "datetime": "2022-06-21 00:00:00",
                        "count": 0.0,
                        "mean": 0.0,
                        "std": 0.0,
                        "min": 0.0,
                        "25%": 0.0,
                        "50%": 0.0,
                        "75%": 0.0,
                        "max": 0.0
                    },
                    {
                        "datetime": "2022-07-05 00:00:00",
                        "count": 0.0,
                        "mean": 0.0,
                        "std": 0.0,
                        "min": 0.0,
                        "25%": 0.0,
                        "50%": 0.0,
                        "75%": 0.0,
                        "max": 0.0
                    },
                    {
                        "datetime": "2022-07-19 00:00:00",
                        "count": 0.0,
                        "mean": 0.0,
                        "std": 0.0,
                        "min": 0.0,
                        "25%": 0.0,
                        "50%": 0.0,
                        "75%": 0.0,
                        "max": 0.0
                    },
                    {
                        "datetime": "2022-08-02 00:00:00",
                        "count": 0.0,
                        "mean": 0.0,
                        "std": 0.0,
                        "min": 0.0,
                        "25%": 0.0,
                        "50%": 0.0,
                        "75%": 0.0,
                        "max": 0.0
                    },
                    {
                        "datetime": "2022-08-16 00:00:00",
                        "count": 0.0,
                        "mean": 0.0,
                        "std": 0.0,
                        "min": 0.0,
                        "25%": 0.0,
                        "50%": 0.0,
                        "75%": 0.0,
                        "max": 0.0
                    },
                    {
                        "datetime": "2022-08-30 00:00:00",
                        "count": 292.0,
                        "mean": 105.56164383561644,
                        "std": 42.80154357025483,
                        "min": 80.0,
                        "25%": 80.0,
                        "50%": 80.0,
                        "75%": 150.0,
                        "max": 550.0
                    },
                    {
                        "datetime": "2022-09-13 00:00:00",
                        "count": -29.0,
                        "mean": 2.4763789780717786,
                        "std": 1.3980220631615623,
                        "min": 0.0,
                        "25%": 0.0,
                        "50%": 0.0,
                        "75%": 0.0,
                        "max": 0.0
                    },
                    {
                        "datetime": "2022-09-27 00:00:00",
                        "count": -32.0,
                        "mean": -16.202524978190368,
                        "std": -10.743705750401098,
                        "min": 0.0,
                        "25%": 0.0,
                        "50%": 0.0,
                        "75%": -50.0,
                        "max": 0.0
                    },
                    {
                        "datetime": "2022-10-11 00:00:00",
                        "count": 2.0,
                        "mean": -2.0329227282017115,
                        "std": -19.23668292581275,
                        "min": 0.0,
                        "25%": 0.0,
                        "50%": 0.0,
                        "75%": 0.0,
                        "max": -306.0
                    },
                    {
                        "datetime": "2022-10-25 00:00:00",
                        "count": -2.0,
                        "mean": 0.5177712130501817,
                        "std": 0.028979959806571642,
                        "min": 0.0,
                        "25%": 0.0,
                        "50%": 0.0,
                        "75%": 0.0,
                        "max": 0.0
                    },
                    {
                        "datetime": "2022-11-08 00:00:00",
                        "count": -16.0,
                        "mean": 3.744769958723438,
                        "std": 4.7898140407203496,
                        "min": 0.0,
                        "25%": 0.0,
                        "50%": 20.0,
                        "75%": 0.0,
                        "max": 36.0
                    },
                    {
                        "datetime": "2022-11-22 00:00:00",
                        "count": -62.0,
                        "mean": 7.529654962760304,
                        "std": -4.908197470655809,
                        "min": 20.0,
                        "25%": 20.0,
                        "50%": 0.0,
                        "75%": 0.0,
                        "max": -36.0
                    }
                ]
            }
        },
        "OneYear": {
            "archive": {
                "count": 0,
                "data": []
            },
            "diff": {
                "count": 0,
                "data": []
            }
        }
    },
    "calc": {
        "latest_date": "2022-11-22 00:00:00",
        "updated_at": "2022-11-22 20:16:52"
    }
}