{
    "price": {
        "current": {
            "datetime": "2022-12-20 00:00:00",
            "count": 51.0,
            "mean": 233.64705882352942,
            "std": 376.31236086684225,
            "min": 80.0,
            "25%": 80.0,
            "50%": 80.0,
            "75%": 80.0,
            "max": 1180.0
        },
        "summary7Days": {
            "datetime": "2022-12-20 00:00:00",
            "count": -12.0,
            "mean": 29.266106442577012,
            "std": 32.94481451250067,
            "min": 0.0,
            "25%": 0.0,
            "50%": 0.0,
            "75%": 0.0,
            "max": 0.0
        },
        "volatility": {
            "weekly": {
                "min": {
                    "basePrice": 80.0,
                    "latestPrice": 80.0,
                    "percent": 0.0
                },
                "50%": {
                    "basePrice": 80.0,
                    "latestPrice": 80.0,
                    "percent": 0.0
                }
            },
            "daily": {
                "min": {
                    "basePrice": 80.0,
                    "latestPrice": 80.0,
                    "percent": 0.0
                },
                "50%": {
                    "basePrice": 80.0,
                    "latestPrice": 80.0,
                    "percent": 0.0
                }
            }
        },
        "weekly": {
            "archive": {
                "count": 7,
                "data": [
                    {
                        "datetime": "2022-12-14 00:00:00",
                        "count": 63.0,
                        "mean": 204.3809523809524,
                        "std": 343.3675463543416,
                        "min": 80.0,
                        "25%": 80.0,
                        "50%": 80.0,
                        "75%": 80.0,
                        "max": 1180.0
                    },
                    {
                        "datetime": "2022-12-15 00:00:00",
                        "count": 62.0,
                        "mean": 206.3870967741936,
                        "std": 345.7981669844329,
                        "min": 80.0,
                        "25%": 80.0,
                        "50%": 80.0,
                        "75%": 80.0,
                        "max": 1180.0
                    },
                    {
                        "datetime": "2022-12-16 00:00:00",
                        "count": 62.0,
                        "mean": 206.3870967741936,
                        "std": 345.798166984433,
                        "min": 80.0,
                        "25%": 80.0,
                        "50%": 80.0,
                        "75%": 80.0,
                        "max": 1180.0
                    },
                    {
                        "datetime": "2022-12-17 00:00:00",
                        "count": 62.0,
                        "mean": 206.3870967741936,
                        "std": 345.7981669844329,
                        "min": 80.0,
                        "25%": 80.0,
                        "50%": 80.0,
                        "75%": 80.0,
                        "max": 1180.0
                    },
                    {
                        "datetime": "2022-12-18 00:00:00",
                        "count": 60.0,
                        "mean": 210.6,
                        "std": 350.81373685490377,
                        "min": 80.0,
                        "25%": 80.0,
                        "50%": 80.0,
                        "75%": 80.0,
                        "max": 1180.0
                    },
                    {
                        "datetime": "2022-12-19 00:00:00",
                        "count": 54.0,
                        "mean": 225.11111111111111,
                        "std": 367.22923110245546,
                        "min": 80.0,
                        "25%": 80.0,
                        "50%": 80.0,
                        "75%": 80.0,
                        "max": 1180.0
                    },
                    {
                        "datetime": "2022-12-20 00:00:00",
                        "count": 51.0,
                        "mean": 233.64705882352942,
                        "std": 376.31236086684225,
                        "min": 80.0,
                        "25%": 80.0,
                        "50%": 80.0,
                        "75%": 80.0,
                        "max": 1180.0
                    }
                ]
            },
            "diff": {
                "count": 7,
                "data": [
                    {
                        "datetime": "2022-12-14 00:00:00",
                        "count": null,
                        "mean": null,
                        "std": null,
                        "min": null,
                        "25%": null,
                        "50%": null,
                        "75%": null,
                        "max": null
                    },
                    {
                        "datetime": "2022-12-15 00:00:00",
                        "count": -1.0,
                        "mean": 2.006144393241186,
                        "std": 2.430620630091312,
                        "min": 0.0,
                        "25%": 0.0,
                        "50%": 0.0,
                        "75%": 0.0,
                        "max": 0.0
                    },
                    {
                        "datetime": "2022-12-16 00:00:00",
                        "count": 0.0,
                        "mean": 0.0,
                        "std": 1.1368683772161603e-13,
                        "min": 0.0,
                        "25%": 0.0,
                        "50%": 0.0,
                        "75%": 0.0,
                        "max": 0.0
                    },
                    {
                        "datetime": "2022-12-17 00:00:00",
                        "count": 0.0,
                        "mean": 0.0,
                        "std": -1.1368683772161603e-13,
                        "min": 0.0,
                        "25%": 0.0,
                        "50%": 0.0,
                        "75%": 0.0,
                        "max": 0.0
                    },
                    {
                        "datetime": "2022-12-18 00:00:00",
                        "count": -2.0,
                        "mean": 4.2129032258064,
                        "std": 5.01556987047087,
                        "min": 0.0,
                        "25%": 0.0,
                        "50%": 0.0,
                        "75%": 0.0,
                        "max": 0.0
                    },
                    {
                        "datetime": "2022-12-19 00:00:00",
                        "count": -6.0,
                        "mean": 14.51111111111112,
                        "std": 16.415494247551692,
                        "min": 0.0,
                        "25%": 0.0,
                        "50%": 0.0,
                        "75%": 0.0,
                        "max": 0.0
                    },
                    {
                        "datetime": "2022-12-20 00:00:00",
                        "count": -3.0,
                        "mean": 8.535947712418306,
                        "std": 9.083129764386797,
                        "min": 0.0,
                        "25%": 0.0,
                        "50%": 0.0,
                        "75%": 0.0,
                        "max": 0.0
                    }
                ]
            }
        },
        "halfYear": {
            "archive": {
                "count": 13,
                "data": [
                    {
                        "datetime": "2022-07-05 00:00:00",
                        "count": 0.0,
                        "mean": 0.0,
                        "std": 0.0,
                        "min": 0.0,
                        "25%": 0.0,
                        "50%": 0.0,
                        "75%": 0.0,
                        "max": 0.0
                    },
                    {
                        "datetime": "2022-07-19 00:00:00",
                        "count": 0.0,
                        "mean": 0.0,
                        "std": 0.0,
                        "min": 0.0,
                        "25%": 0.0,
                        "50%": 0.0,
                        "75%": 0.0,
                        "max": 0.0
                    },
                    {
                        "datetime": "2022-08-02 00:00:00",
                        "count": 0.0,
                        "mean": 0.0,
                        "std": 0.0,
                        "min": 0.0,
                        "25%": 0.0,
                        "50%": 0.0,
                        "75%": 0.0,
                        "max": 0.0
                    },
                    {
                        "datetime": "2022-08-16 00:00:00",
                        "count": 36.0,
                        "mean": 117.22222222222224,
                        "std": 169.3620148188255,
                        "min": 80.0,
                        "25%": 80.0,
                        "50%": 80.0,
                        "75%": 80.0,
                        "max": 1080.0
                    },
                    {
                        "datetime": "2022-08-30 00:00:00",
                        "count": 27.0,
                        "mean": 170.37037037037038,
                        "std": 280.3360823874071,
                        "min": 80.0,
                        "25%": 80.0,
                        "50%": 80.0,
                        "75%": 80.0,
                        "max": 1180.0
                    },
                    {
                        "datetime": "2022-09-13 00:00:00",
                        "count": 1.0,
                        "mean": 100.0,
                        "std": 226.26595720833777,
                        "min": 100.0,
                        "25%": 100.0,
                        "50%": 100.0,
                        "75%": 100.0,
                        "max": 100.0
                    },
                    {
                        "datetime": "2022-09-27 00:00:00",
                        "count": 39.0,
                        "mean": 81.28205128205128,
                        "std": 5.702948073947637,
                        "min": 80.0,
                        "25%": 80.0,
                        "50%": 80.0,
                        "75%": 80.0,
                        "max": 110.0
                    },
                    {
                        "datetime": "2022-10-11 00:00:00",
                        "count": 55.0,
                        "mean": 135.4181818181818,
                        "std": 229.0054738880865,
                        "min": 80.0,
                        "25%": 80.0,
                        "50%": 80.0,
                        "75%": 80.0,
                        "max": 1080.0
                    },
                    {
                        "datetime": "2022-10-25 00:00:00",
                        "count": 60.0,
                        "mean": 295.1333333333333,
                        "std": 434.00232236614704,
                        "min": 80.0,
                        "25%": 80.0,
                        "50%": 80.0,
                        "75%": 80.0,
                        "max": 1180.0
                    },
                    {
                        "datetime": "2022-11-08 00:00:00",
                        "count": 55.0,
                        "mean": 314.8363636363636,
                        "std": 448.3918079849514,
                        "min": 80.0,
                        "25%": 80.0,
                        "50%": 80.0,
                        "75%": 84.0,
                        "max": 1180.0
                    },
                    {
                        "datetime": "2022-11-22 00:00:00",
                        "count": 78.0,
                        "mean": 250.9743589743589,
                        "std": 395.6650483715115,
                        "min": 80.0,
                        "25%": 80.0,
                        "50%": 80.0,
                        "75%": 80.0,
                        "max": 1180.0
                    },
                    {
                        "datetime": "2022-12-06 00:00:00",
                        "count": 69.0,
                        "mean": 257.3333333333333,
                        "std": 401.3703976110239,
                        "min": 80.0,
                        "25%": 80.0,
                        "50%": 80.0,
                        "75%": 80.0,
                        "max": 1180.0
                    },
                    {
                        "datetime": "2022-12-20 00:00:00",
                        "count": 51.0,
                        "mean": 233.64705882352942,
                        "std": 376.31236086684225,
                        "min": 80.0,
                        "25%": 80.0,
                        "50%": 80.0,
                        "75%": 80.0,
                        "max": 1180.0
                    }
                ]
            },
            "diff": {
                "count": 13,
                "data": [
                    {
                        "datetime": "2022-07-05 00:00:00",
                        "count": null,
                        "mean": null,
                        "std": null,
                        "min": null,
                        "25%": null,
                        "50%": null,
                        "75%": null,
                        "max": null
                    },
                    {
                        "datetime": "2022-07-19 00:00:00",
                        "count": 0.0,
                        "mean": 0.0,
                        "std": 0.0,
                        "min": 0.0,
                        "25%": 0.0,
                        "50%": 0.0,
                        "75%": 0.0,
                        "max": 0.0
                    },
                    {
                        "datetime": "2022-08-02 00:00:00",
                        "count": 0.0,
                        "mean": 0.0,
                        "std": 0.0,
                        "min": 0.0,
                        "25%": 0.0,
                        "50%": 0.0,
                        "75%": 0.0,
                        "max": 0.0
                    },
                    {
                        "datetime": "2022-08-16 00:00:00",
                        "count": 36.0,
                        "mean": 117.22222222222224,
                        "std": 169.3620148188255,
                        "min": 80.0,
                        "25%": 80.0,
                        "50%": 80.0,
                        "75%": 80.0,
                        "max": 1080.0
                    },
                    {
                        "datetime": "2022-08-30 00:00:00",
                        "count": -9.0,
                        "mean": 53.14814814814814,
                        "std": 110.9740675685816,
                        "min": 0.0,
                        "25%": 0.0,
                        "50%": 0.0,
                        "75%": 0.0,
                        "max": 100.0
                    },
                    {
                        "datetime": "2022-09-13 00:00:00",
                        "count": -26.0,
                        "mean": -70.37037037037038,
                        "std": -54.07012517906932,
                        "min": 20.0,
                        "25%": 20.0,
                        "50%": 20.0,
                        "75%": 20.0,
                        "max": -1080.0
                    },
                    {
                        "datetime": "2022-09-27 00:00:00",
                        "count": 38.0,
                        "mean": -18.717948717948715,
                        "std": -220.56300913439014,
                        "min": -20.0,
                        "25%": -20.0,
                        "50%": -20.0,
                        "75%": -20.0,
                        "max": 10.0
                    },
                    {
                        "datetime": "2022-10-11 00:00:00",
                        "count": 16.0,
                        "mean": 54.13613053613052,
                        "std": 223.30252581413887,
                        "min": 0.0,
                        "25%": 0.0,
                        "50%": 0.0,
                        "75%": 0.0,
                        "max": 970.0
                    },
                    {
                        "datetime": "2022-10-25 00:00:00",
                        "count": 5.0,
                        "mean": 159.71515151515152,
                        "std": 204.99684847806054,
                        "min": 0.0,
                        "25%": 0.0,
                        "50%": 0.0,
                        "75%": 0.0,
                        "max": 100.0
                    },
                    {
                        "datetime": "2022-11-08 00:00:00",
                        "count": -5.0,
                        "mean": 19.70303030303029,
                        "std": 14.389485618804372,
                        "min": 0.0,
                        "25%": 0.0,
                        "50%": 0.0,
                        "75%": 4.0,
                        "max": 0.0
                    },
                    {
                        "datetime": "2022-11-22 00:00:00",
                        "count": 23.0,
                        "mean": -63.86200466200472,
                        "std": -52.726759613439924,
                        "min": 0.0,
                        "25%": 0.0,
                        "50%": 0.0,
                        "75%": -4.0,
                        "max": 0.0
                    },
                    {
                        "datetime": "2022-12-06 00:00:00",
                        "count": -9.0,
                        "mean": 6.358974358974422,
                        "std": 5.7053492395124294,
                        "min": 0.0,
                        "25%": 0.0,
                        "50%": 0.0,
                        "75%": 0.0,
                        "max": 0.0
                    },
                    {
                        "datetime": "2022-12-20 00:00:00",
                        "count": -18.0,
                        "mean": -23.686274509803894,
                        "std": -25.058036744181663,
                        "min": 0.0,
                        "25%": 0.0,
                        "50%": 0.0,
                        "75%": 0.0,
                        "max": 0.0
                    }
                ]
            }
        },
        "OneYear": {
            "archive": {
                "count": 0,
                "data": []
            },
            "diff": {
                "count": 0,
                "data": []
            }
        }
    },
    "calc": {
        "latest_date": "2022-12-20 00:00:00",
        "updated_at": "2022-12-20 20:14:07"
    }
}